whatschecker/__init__.py
whatschecker/__main__.py
whatschecker/cli.py
whatschecker/logger_setup.py
whatschecker-0.1.0.dist-info/licenses/LICENSE
whatschecker-0.1.0.dist-info/METADATA
whatschecker-0.1.0.dist-info/WHEEL
whatschecker-0.1.0.dist-info/entry_points.txt
whatschecker-0.1.0.dist-info/top_level.txt
whatschecker-0.1.0.dist-info/RECORD
