Metadata-Version: 2.4
Name: whatschecker
Version: 0.1.0
Summary: Discover who uses WhatsApp and Extract
Author-email: Hasan Rasel <rrss.mahmud@gmail.com>
License-Expression: LicenseRef-Proprietary
Project-URL: Homepage, https://github.com/bitbytelab/WhatsChecker
Project-URL: Issues, https://github.com/bitbytelab/WhatsChecker/issues
Keywords: WhatsApp Checker,WhatsApp,Checker,WhatsApp Validator
Classifier: Intended Audience :: Developers
Classifier: Intended Audience :: Education
Classifier: Operating System :: OS Independent
Classifier: Programming Language :: Python :: 3
Classifier: Topic :: Communications :: Chat
Classifier: Topic :: Communications :: Telephony
Classifier: Topic :: Internet :: WWW/HTTP :: HTTP Servers
Classifier: Topic :: Software Development :: Build Tools
Classifier: Topic :: Software Development :: Libraries :: Python Modules
Requires-Python: >=3.9
License-File: LICENSE
Requires-Dist: undetected-chromedriver
Requires-Dist: selenium
Dynamic: license-file
